pymutantic/DETAILS.md
pymutantic/__init__.py
pymutantic/_json_path.py
pymutantic/_migrate.py
pymutantic/_mutant.py
pymutantic/test_json_path.py
pymutantic/test_migrate.py
pymutantic/test_mutant.py
pymutantic-0.10.0.dist-info/LICENSE
pymutantic-0.10.0.dist-info/METADATA
pymutantic-0.10.0.dist-info/WHEEL
pymutantic-0.10.0.dist-info/RECORD
