Metadata-Version: 2.1
Name: pymutantic
Version: 0.10.0
Summary: 
Author: Daniel Bradburn
Author-email: daniel.bradburn@crunchr.com
Requires-Python: >=3.11,<4.0
Classifier: Programming Language :: Python :: 3
Classifier: Programming Language :: Python :: 3.11
Classifier: Programming Language :: Python :: 3.12
Requires-Dist: jsonpath-ng (>=1.6.1,<2.0.0)
Requires-Dist: munch (>=4.0.0,<5.0.0)
Requires-Dist: pycrdt (>=0.9.7,<0.10.0)
Requires-Dist: pydantic (>=2.7,<3.0)
Requires-Dist: toolz (>=0.12.1,<0.13.0)
